RISC-V.srcs/sources_1/new/mux.v
`timescale 1ns / 1ps
//////////////////////////////////////////////////////////////////////////////////
// Company: 
// Engineer: 
// 
// Create Date: 02/08/2024 12:09:34 PM
// Design Name: 
// Module Name: mux2
// Project Name: 
// Target Devices: 
// Tool Versions: 
// Description: 
// 
// Dependencies: 
// 
// Revision:
// Revision 0.01 - File Created
// Additional Comments:
// 
//////////////////////////////////////////////////////////////////////////////////


module mux(
    input  [63:0] A,
    input  [63:0] B,
    input  [63:0] C,
    input  [63:0] D,
    input  [63:0] E,
    input  [63:0] F,
    input  [63:0] G,
    input  [63:0] H,
    input  [2:0] ctrl,
    output reg [63:0] Y
    );
    
    always @(*) begin
        case (ctrl)
            3'b000: Y <= A;
            3'b001: Y <= B;
            3'b010: Y <= C;
            3'b011: Y <= D;
            3'b100: Y <= E;
            3'b101: Y <= F;
            3'b110: Y <= G;
            3'b111: Y <= H;
        endcase
    end
endmodule


module mux2(
    input  [63:0] A,
    input  [63:0] B,
    input  ctrl,
    output [63:0] Y
    );
    
    /*always @(*) begin
        case (ctrl)
            3'b110: Y <= A;
            3'b111: Y <= B;
        endcase
    end*/

   assign Y = ctrl ? B : A;
endmodule

dmem.v
module dmem(
	input clk,
	
	input [63:0] a1,
	input we1,
	input [63:0] wd1,
	output [63:0] rd1,

	input [63:0] a2,
	input we2,
	input [63:0] wd2,
	output [63:0] rd2,

	input [63:0] a3,
	output [63:0] rd3
    );


	integer i; //initialize it to 0 so there arent a bunch of X everywhere (scary twitter)
	initial begin
		for (i = 0; i < 1024; i = i + 1) begin
			data[i] <= 64'b0;
	//		$dumpvars(0, data[i]);
		end
	end

	
	reg [63:0] data [1023:0];   

	always @(posedge clk) begin
		if(we1) begin
			data[a1] <= wd1;		
		end
		if(we2) begin
			data[a2] <= wd2;
		end
	end


//array of size 32 containing 64 bit integers
	
	assign rd1 = data[a1];
	assign rd2 = data[a2];
	assign rd3 = data[a3];
endmodule

alu.v
//////////////////////////////////////////////////////////////////////////////////
// Company: 
// Engineer: 
// 
// Create Date: 04/03/2021 08:14:19 PM
// Design Name: 
// Module Name: alu
// Project Name: 
// Target Devices: 
// Tool Versions: 
// Description: 
// 
// Dependencies: 
// 
// Revision: 
// Revision 0.01 - File Created
// Additional Comments:
// 
//////////////////////////////////////////////////////////////////////////////////


module alu(
	input [63:0] a,
	input [63:0] b,
	input [6:0] f,
	output [63:0] y,
	output zero
	);
    
	wire [63:0] aa, bb;
	wire [63:0] _and, _or, _xor, _sum, _slt, _sgt, _seq, _mul, _lshift, _rshift;
	wire [64:0] _carry, true_sum;
	wire [127:0] _mul_carry;

	reg [63:0] _y;

	assign aa = f[6] ? ~a : a;
	assign bb = f[5] ? ~b : b;
	
	assign _and = aa & bb;
	assign _or = aa | bb;
	assign _xor = aa ^ bb;

	assign true_sum = aa+bb+ (f[6] | f[5]);

	assign _sum = true_sum[63:0];
	assign _carry = true_sum[64];
	assign _slt = _sum[63] >> 63;

	and_64_bit and_64_bit1(~_xor, _seq);

	assign _sgt = ~(_seq & _slt) >> 63;

	assign _mul = aa * bb;
	assign _mul_carry = aa*bb;
	
	assign _lshift = aa << bb;
	assign _rshift = aa >> bb;

	always @(*) begin
		case (f[4:1]) 
			4'h0: _y <= _and;
			4'h1: _y <= _or;
			4'h2: _y <= _xor;
			4'h3: _y <= _sum;
			4'h4: _y <= 64'h0 | _slt;
			4'h5: _y <= 64'h0 | _sgt;
			4'h6: _y <= 64'h0 | _seq;
			4'h7: _y <= _carry[64];
			4'h8: _y <= _mul;
			4'h9: _y <= _mul_carry[127:64];
			4'hA: _y <= _lshift;
			4'hB: _y <= _rshift;
			4'hC: _y <= 64'h0000_0000;
			4'hD: _y <= 64'h0000_0000;
			4'hE: _y <= 64'h0000_0000;
			4'hF: _y <= 64'h0000_0000;
		endcase
	end

	assign y = f[0] ? ~_y : _y;
	assign zero = ( y == 64'b0 );
endmodule

module and_64_bit(
	input [63:0] A,
	output [63:0] y
	);
	
	assign y = 64'h0 | A[0] & A[1] & A[2] & A[3] & A[4] & A[5] & A[6] & A[7] & A[8] & A[9] & A[10] & A[11] & A[12] & A[13] & A[14] & A[15] & A[16] & A[17] & A[18] & A[19] & A[20] & A[21] & A[22] & A[23] & A[24] & A[25] & A[26] & A[27] & A[28] & A[29] & A[30] & A[31] & A[32] & A[33] & A[34] & A[35] & A[36] & A[37] & A[38] & A[39] & A[40] & A[41] & A[42] & A[43] & A[44] & A[45] & A[46] & A[47] & A[48] & A[49] & A[50] & A[51] & A[52] & A[53] & A[54] & A[55] & A[56] & A[57] & A[58] & A[59] & A[60] & A[61] & A[62] & A[63];

endmodule

RISC-V.srcs/sources_1/new/registerfile.v
`timescale 1ns / 1ps
//////////////////////////////////////////////////////////////////////////////////
// Company: 
// Engineer: 
// 
// Create Date: 02/16/2024 08:48:15 PM
// Design Name: 
// Module Name: registerfile
// Project Name: 
// Target Devices: 
// Tool Versions: 
// Description: 
// 
// Dependencies: 
// 
// Revision:
// Revision 0.01 - File Created
// Additional Comments:
// 
//////////////////////////////////////////////////////////////////////////////////


module registerfile(
	input clk,
	input WE3,

	input [9:0] a1,
	input [9:0] a2,
	input [9:0] a3,

	input [63:0] wd3,

	output [63:0] rd1,
	output [63:0] rd2
    );

	reg [63:0] data [1023:0];

	integer i; //initialize it to 0 so there arent a bunch of X everywhere (scary twitter)
	initial begin
		for (i = 0; i < 1024; i = i + 1) begin
			data[i] <= 64'b0;
		end
	end

	always @(posedge clk)
		if (WE3 && a3) //&& a3 prevents writing if a3 is 0, so register 0 cannot be written to.
			data[a3] <= wd3;
	
	assign rd1 = data[a1];
	assign rd2 = data[a2];

endmodule

control.v
`timescale 1ns / 1ps
//////////////////////////////////////////////////////////////////////////////////
// Company: 
// Engineer: 
// 
// Create Date: 02/12/2024 04:51:29 PM
// Design Name: 
// Module Name: control
// Project Name: 
// Target Devices: 
// Tool Versions: 
// Description: 
// 
// Dependencies: 
// 
// Revision:
// Revision 0.01 - File Created
// Additional Comments:
// 
//////////////////////////////////////////////////////////////////////////////////


module control(
	input [11:0] opcode,

	output [7:0] ALUOp,

	output ALUSrcA,
	output ALUSrcB,
	output MemWrite,
	output RegWrite,
	
	output PCSrc,
	output WDSrc,
	output IMMSrc,
	output IMemWrite
    );

    reg [15:0] control = 16'h0000;


    always @(*) begin
	case(opcode)
		//R TYPE
		12'h000: control <= 16'b0000_1000_0000_0110; //add
		12'h001: control <= 16'b0000_1000_0010_0110; //sub
		12'h002: control <= 16'b0000_1000_0001_0000; //mul
		12'h003: control <= 16'b0000_1000_0000_0000; //and
		12'h004: control <= 16'b0000_1000_0000_0010; //or
		12'h005: control <= 16'b0000_1000_0000_0100; //xor
		12'h006: control <= 16'b0000_1000_0000_1000; //slt
		12'h007: control <= 16'b0000_1000_0000_1010; //sgt
		12'h008: control <= 16'b0000_1000_0000_1100; //seq
		12'h009: control <= 16'b0000_1000_0000_1110; //addc
		12'h00A: control <= 16'b0000_1000_0001_0010; //mulc
		12'h00B: control <= 16'b0000_1000_0001_0100; //lshift
		12'h00C: control <= 16'b0000_1000_0001_0110; //rshift
		//D E F are reserved for "later"
		
		//I TYPE
		12'h100: control <= 16'b0000_1010_0000_0110; //addi
		12'h101: control <= 16'b0000_1010_0010_0110; //subi
		12'h102: control <= 16'b0000_1010_0001_0000; //muli
		12'h103: control <= 16'b0000_1010_0000_0000; //andi
		12'h104: control <= 16'b0000_1010_0000_0010; //ori
		12'h105: control <= 16'b0000_1010_0000_0100; //xori
		12'h106: control <= 16'b0000_1010_0000_1000; //slti
		12'h107: control <= 16'b0000_1010_0000_1010; //sgti
		12'h108: control <= 16'b0000_1010_0000_1100; //seqi
		12'h109: control <= 16'b0000_1010_0000_1110; //addci
		12'h10A: control <= 16'b0000_1010_0001_0010; //mulci
		12'h10B: control <= 16'b0000_1010_0001_0100; //lshifti
		12'h10C: control <= 16'b0000_1010_0001_0110; //rshifti
		//D E F are reserved to be used soon(tm)

		//S TYPE
		12'h200: control <= 16'b0000_0110_0000_0110; //sw
		12'h201: control <= 16'b1000_0000_0000_0110; //sImem
		
		//L TYPE
		12'h300: control <= 16'b0110_1010_0000_0110; //lw

		//jump
		12'h420: control <= 16'b0101_0000_0000_0000; //jtl
		12'h421: control <= 16'b0101_0000_0000_1100; //beq
		12'h422: control <= 16'b0101_0000_0000_1000; //blt
		12'h423: control <= 16'b0101_0000_0000_1010; //bgt
	endcase
    end

    assign ALUOp = control[7:0];
    
    assign ALUSrcA = control[8];
    assign ALUSrcB = control[9];
    assign MemWrite = control[10];
    assign RegWrite = control[11];
    
    assign PCSrc = control[12];
    assign WDSrc = control[13];
    assign IMMSrc = control[14];
    assign IMemWrite = control[15];

endmodule

imem.sv
module imem(
	input [63:0] a,
	output [63:0] inst
    );


	reg [63:0] instructions [63:0];   
//array of size 32 containing 64 bit integers

	initial begin 
		$readmemb("./bin.mem", instructions, 0, 63);
	end


	assign inst = instructions[a];
    
endmodule

module imem_mut(
	input [31:0] a2,
	input [63:0] wd2,
	input we,
	
	input [31:0] a,
	output [63:0] inst
    );


	reg [63:0] instructions [63:0];   
//array of size 64 containing 64 bit integers


    always @(posedge we) begin
        instructions[a2] <= wd2;
    end

	assign inst = instructions[a];
    
endmodule

main.v
`timescale 1ns / 1ps
//////////////////////////////////////////////////////////////////////////////////
// Company: 
// Engineer: 
// 
// Create Date: 02/12/2024 04:29:56 PM
// Design Name: 
// Module Name: main
// Project Name: 
// Target Devices: 
// Tool Versions: 
// Description: 
// 
// Dependencies: 
// 
// Revision:
// Revision 0.01 - File Created
// Additional Comments:
// 
//////////////////////////////////////////////////////////////////////////////////


module main(
	input clk,
	input reset,
	input [63:0] kbin,
	input [63:0] wordAddress,
	output [63:0] readWord
     );


	reg [63:0] PC;
	wire [63:0] PCNext;
	wire [63:0] Instruction;
	wire [63:0] PCPlusOne = PC + 1;
	

	always @(posedge clk) begin
		PC = PCNext; 
	end

	always @(posedge reset) begin
		PC = 0;
	end

	//Instruction Mem
	imem imem1(PC, Instruction);

	//Control Unit
	wire [7:0] ALUOp;
	wire ALUSrcAControl, ALUSrcBControl, MemWriteControl, RegWriteControl, PCSrcControl, WDSrcControl, IMMSrcControl, IMemWriteControl;

	control control1(Instruction[11:0], ALUOp, ALUSrcAControl, ALUSrcBControl, MemWriteControl, RegWriteControl, PCSrcControl, WDSrcControl, IMMSrcControl, IMemWriteControl);
	
	//Register File
	wire [63:0] WriteDataSource;
	wire [63:0] RegRead1, RegRead2;
	wire [9:0] A1, A2, A3;
	assign A1 = Instruction[31:22];
	assign A2 = Instruction[41:32];
	assign A3 = Instruction[21:12];

	registerfile registerfile1(clk, RegWriteControl, A1, A2, A3, WriteDataSource, RegRead1, RegRead2);
	
	//Immediate
	wire [63:0] Immediate;

	wire [21:0] ImmediateSmall = Instruction[63:42];
	wire [31:0] ImmediateBig = Instruction[63:32];

	wire [63:0] ExtendedImmediateSmall = ImmediateSmall[21] ? 64'b1 & ImmediateSmall : 64'b0 | ImmediateSmall;
	wire [63:0] ExtendedImmediateBig = ImmediateBig[31] ? 64'b1 & ImmediateBig : 64'b0 | ImmediateBig;
	
	assign Immediate = IMMSrcControl ? ImmediateSmall : ImmediateBig;

	//ALU Sources
	wire [63:0] ALUSrcA, ALUSrcB;
	mux2 ALUSrcAMux(RegRead1, PC, ALUSrcAControl, ALUSrcA);
	mux2 ALUSrcBMux(RegRead2, Immediate, ALUSrcBControl, ALUSrcB);

	//ALU
	wire [63:0] ALUOut;
	wire zero;
	wire [6:0] SizedALUOp = ALUOp[6:0];
	alu alu1(ALUSrcA, ALUSrcB, SizedALUOp, ALUOut, zero);
	
	
	//Data memory
	wire [63:0] empty, empty3, empty4, empty5, empty6;
	wire empty2;
	wire [63:0] MemRead;
	
	dmem dmem1(clk,
		ALUOut, MemWriteControl, RegRead2, MemRead, 
		(64'b0 | 1'b1), 1'b1, kbin, empty4, 
		wordAddress, readWord);

	//Writeback
	mux2 wdsourcemux(ALUOut, MemRead, WDSrcControl, WriteDataSource);

	//PC Next //at the end
	wire notzero = ~zero;
	wire PCAndZero = PCSrcControl & notzero;

	mux2 pcNextMux(PCPlusOne, Immediate, PCAndZero, PCNext);

	//smem smem1(clk, PCNext, PC);

endmodule

driver.sv
module testMain();

        reg clk;
        reg reset;
        reg [63:0] counter = 0;
        reg [63:0] activeKeyStroke;
	reg [63:0] wordToRead = 64'h201;

        reg [63:0] keystrokes [63:0];
	
	wire [63:0] readWord;

        main main1(clk, reset, activeKeyStroke, wordToRead, readWord);

        initial begin
                $readmemh("keystrokes.mem", keystrokes, 0, 63);
                reset = 1; #50;
                reset = 0; #50;
		
		//$dumpfile("dump.vcd");
		//$dumpvars(0, main1);
        end

        always begin
                activeKeyStroke <= keystrokes[counter/10];
                // /10 gives enough time for cpu to process keyboard input
                clk = 0; #50;
                clk = 1; #50;

                counter = counter+1;

		if(counter >= 16'h200) begin
			$write("%0c", readWord); #10;
			wordToRead = wordToRead + 1; #10;
			if (wordToRead == 64'h0000_0000_0000_0003) begin 
				$finish;
			end
		end
        end
endmodule

dump.vcd
$date
	Fri Feb 23 13:46:07 2024
$end
$version
	Icarus Verilog
$end
$timescale
	1ps
$end
$scope module testMain $end
$scope module main1 $end
$var wire 1 ! PCAndZero $end
$var wire 1 " clk $end
$var wire 64 # kbin [63:0] $end
$var wire 1 $ notzero $end
$var wire 1 % reset $end
$var wire 64 & wordAddress [63:0] $end
$var wire 1 ' zero $end
$var wire 64 ( readWord [63:0] $end
$var wire 64 ) empty4 [63:0] $end
$var wire 64 * WriteDataSource [63:0] $end
$var wire 1 + WDSrcControl $end
$var wire 7 , SizedALUOp [6:0] $end
$var wire 1 - RegWriteControl $end
$var wire 64 . RegRead2 [63:0] $end
$var wire 64 / RegRead1 [63:0] $end
$var wire 1 0 PCSrcControl $end
$var wire 64 1 PCPlusOne [63:0] $end
$var wire 64 2 PCNext [63:0] $end
$var wire 1 3 MemWriteControl $end
$var wire 64 4 MemRead [63:0] $end
$var wire 64 5 Instruction [63:0] $end
$var wire 22 6 ImmediateSmall [21:0] $end
$var wire 32 7 ImmediateBig [31:0] $end
$var wire 64 8 Immediate [63:0] $end
$var wire 1 9 IMemWriteControl $end
$var wire 1 : IMMSrcControl $end
$var wire 64 ; ExtendedImmediateSmall [63:0] $end
$var wire 64 < ExtendedImmediateBig [63:0] $end
$var wire 1 = ALUSrcBControl $end
$var wire 64 > ALUSrcB [63:0] $end
$var wire 1 ? ALUSrcAControl $end
$var wire 64 @ ALUSrcA [63:0] $end
$var wire 64 A ALUOut [63:0] $end
$var wire 8 B ALUOp [7:0] $end
$var wire 10 C A3 [9:0] $end
$var wire 10 D A2 [9:0] $end
$var wire 10 E A1 [9:0] $end
$var reg 64 F PC [63:0] $end
$scope module ALUSrcAMux $end
$var wire 64 G B [63:0] $end
$var wire 1 ? ctrl $end
$var wire 64 H Y [63:0] $end
$var wire 64 I A [63:0] $end
$upscope $end
$scope module ALUSrcBMux $end
$var wire 64 J B [63:0] $end
$var wire 1 = ctrl $end
$var wire 64 K Y [63:0] $end
$var wire 64 L A [63:0] $end
$upscope $end
$scope module alu1 $end
$var wire 64 M _and [63:0] $end
$var wire 64 N _or [63:0] $end
$var wire 64 O _xor [63:0] $end
$var wire 64 P a [63:0] $end
$var wire 64 Q b [63:0] $end
$var wire 7 R f [6:0] $end
$var wire 1 ' zero $end
$var wire 64 S y [63:0] $end
$var wire 65 T true_sum [64:0] $end
$var wire 64 U bb [63:0] $end
$var wire 64 V aa [63:0] $end
$var wire 64 W _sum [63:0] $end
$var wire 64 X _slt [63:0] $end
$var wire 64 Y _sgt [63:0] $end
$var wire 64 Z _seq [63:0] $end
$var wire 64 [ _rshift [63:0] $end
$var wire 128 \ _mul_carry [127:0] $end
$var wire 64 ] _mul [63:0] $end
$var wire 64 ^ _lshift [63:0] $end
$var wire 65 _ _carry [64:0] $end
$var reg 64 ` _y [63:0] $end
$scope module and_64_bit1 $end
$var wire 64 a A [63:0] $end
$var wire 64 b y [63:0] $end
$upscope $end
$upscope $end
$scope module control1 $end
$var wire 12 c opcode [11:0] $end
$var wire 1 + WDSrc $end
$var wire 1 - RegWrite $end
$var wire 1 0 PCSrc $end
$var wire 1 3 MemWrite $end
$var wire 1 9 IMemWrite $end
$var wire 1 : IMMSrc $end
$var wire 1 = ALUSrcB $end
$var wire 1 ? ALUSrcA $end
$var wire 8 d ALUOp [7:0] $end
$var reg 16 e control [15:0] $end
$upscope $end
$scope module dmem1 $end
$var wire 64 f a1 [63:0] $end
$var wire 64 g a2 [63:0] $end
$var wire 64 h a3 [63:0] $end
$var wire 1 " clk $end
$var wire 64 i rd1 [63:0] $end
$var wire 64 j rd2 [63:0] $end
$var wire 64 k rd3 [63:0] $end
$var wire 64 l wd2 [63:0] $end
$var wire 1 3 we1 $end
$var wire 1 m we2 $end
$var wire 64 n wd1 [63:0] $end
$var integer 32 o i [31:0] $end
$upscope $end
$scope module imem1 $end
$var wire 64 p a [63:0] $end
$var wire 64 q inst [63:0] $end
$upscope $end
$scope module pcNextMux $end
$var wire 64 r A [63:0] $end
$var wire 64 s B [63:0] $end
$var wire 1 ! ctrl $end
$var wire 64 t Y [63:0] $end
$upscope $end
$scope module registerfile1 $end
$var wire 1 - WE3 $end
$var wire 10 u a1 [9:0] $end
$var wire 10 v a2 [9:0] $end
$var wire 10 w a3 [9:0] $end
$var wire 1 " clk $end
$var wire 64 x rd1 [63:0] $end
$var wire 64 y rd2 [63:0] $end
$var wire 64 z wd3 [63:0] $end
$var integer 32 { i [31:0] $end
$upscope $end
$scope module wdsourcemux $end
$var wire 64 | A [63:0] $end
$var wire 64 } B [63:0] $end
$var wire 1 + ctrl $end
$var wire 64 ~ Y [63:0] $end
$upscope $end
$upscope $end
$upscope $end
$enddefinitions $end
#100000000000000
$dumpvars
b1000000000 ~
b0 }
b1000000000 |
b10000000000 {
b1000000000 z
b0 y
b0 x
b10 w
b1000000000 v
b0 u
b10 t
b1000000000 s
b10 r
b100000000000000000000000000010000100000000 q
b1 p
b10000000000 o
b0 n
1m
b1001100 l
b0 k
b1001100 j
b0 i
b1000000001 h
b1 g
b1000000000 f
b101000000110 e
b110 d
b100000000 c
b0 b
b1111111111111111111111111111111111111111111111111111110111111111 a
b1000000000 `
b0 _
b0 ^
b0 ]
b0 \
b0 [
b0 Z
b1 Y
b0 X
b1000000000 W
b0 V
b1000000000 U
b1000000000 T
b1000000000 S
b110 R
b1000000000 Q
b0 P
b1000000000 O
b1000000000 N
b0 M
b0 L
b1000000000 K
b1000000000 J
b0 I
b0 H
b1 G
b1 F
b0 E
b1000000000 D
b10 C
b110 B
b1000000000 A
b0 @
0?
b1000000000 >
1=
b1000000000 <
b0 ;
0:
09
b1000000000 8
b1000000000 7
b0 6
b100000000000000000000000000010000100000000 5
b0 4
03
b10 2
b10 1
00
b0 /
b0 .
1-
b110 ,
0+
b1000000000 *
b1001100 )
b0 (
0'
b1000000001 &
0%
1$
b1001100 #
0"
0!
$end
#150000000000000
0$
b0 *
b0 z
b0 ~
1'
b0 A
b0 S
b0 f
b0 |
b0 `
b1 Z
b1 b
b1111111111111111111111111111111111111111111111111111111111111111 a
b0 W
b0 O
b0 N
b0 T
b0 U
b0 <
b0 >
b0 K
b0 Q
b0 8
b0 J
b0 s
b11 2
b11 t
b0 7
b1100001 C
b1100001 w
b0 D
b0 v
b11 1
b11 r
b1100001000100000000 5
b1100001000100000000 q
b10 F
b10 G
b10 p
1"
#200000000000000
0"
#250000000000000
1$
b1001100 *
b1001100 z
b1001100 ~
0'
b1001100 4
b1001100 i
b1001100 }
b1 A
b1 S
b1 f
b1 |
1+
1:
b1 `
b110101000000110 e
b0 Z
b0 b
b1111111111111111111111111111111111111111111111111111111111111110 a
b1 W
b1 O
b1 N
b1 T
b1 U
b10000000000 <
b1 >
b1 K
b1 Q
b1 ;
b1 8
b1 J
b1 s
b100 2
b100 t
b10000000000 7
b1 6
b1 C
b1 w
b1100000000 c
b100 1
b100 r
b1000000000000000000000000000001001100000000 5
b1000000000000000000000000000001001100000000 q
b11 F
b11 G
b11 p
1"
#300000000000000
0"
#350000000000000
0$
1'
b1100 ,
b1100 R
0!
b0 *
b0 z
b0 ~
b0 ]
b0 \
b1001100 ^
b1001100 [
b1001100 V
b0 4
b0 i
b0 }
b0 A
b0 S
b0 f
b0 |
b1100 B
b1100 d
0=
0-
10
0+
b1001100 @
b1001100 H
b1001100 P
b0 `
b101000000001100 e
b1001100 /
b1001100 I
b1001100 x
b1111111111111111111111111111111111111111111111111111111110110011 a
b1001100 W
b1001100 O
b1001100 N
b1001100 T
b0 U
b110001100001 <
b11 ;
b0 >
b0 K
b0 Q
b11 8
b11 J
b11 s
b101 2
b101 t
b110001100001 7
b11 6
b0 C
b0 w
b1100001 D
b1100001 v
b1 E
b1 u
b10000100001 c
b101 1
b101 r
b11000110000100000000010000000000010000100001 5
b11000110000100000000010000000000010000100001 q
b100 F
b100 G
b100 p
1"
#400000000000000
0"
#450000000000000
1$
b1001100 *
b1001100 z
b1001100 ~
0'
b1001100 A
b1001100 S
b1001100 f
b1001100 |
b1001100 `
b110 ,
b110 R
b110 B
b110 d
1=
1-
00
0:
b101000000110 e
b0 <
b0 ;
b0 8
b0 J
b0 s
b110 2
b110 t
b0 7
b0 6
b1100001 C
b1100001 w
b0 D
b0 v
b100000000 c
b110 1
b110 r
b10001100001000100000000 5
b10001100001000100000000 q
b101 F
b101 G
b101 p
1"
#500000000000000
0"
#550000000000000
0$
1'
b0 *
b0 z
b0 ~
b1100 ,
b1100 R
0!
b0 4
b0 i
b0 }
b0 A
b0 S
b0 f
b0 |
b1100 B
b1100 d
0=
0-
10
1:
b0 `
b101000000001100 e
b1111111111111111111111111111111111111111111111111111111110110011 a
b1001100 U
b1001100 W
b1001100 O
b1001100 N
b110000000001 <
b1001100 >
b1001100 K
b1001100 Q
b11 ;
b1001100 T
b0 ^
b0 [
b0 V
b11 8
b11 J
b11 s
b0 @
b0 H
b0 P
b111 2
b111 t
b110000000001 7
b11 6
b0 C
b0 w
b1001100 .
b1001100 L
b1001100 n
b1001100 y
b1 D
b1 v
b0 /
b0 I
b0 x
b0 E
b0 u
b10000100001 c
b111 1
b111 r
b11000000000100000000000000000000010000100001 5
b11000000000100000000000000000000010000100001 q
b110 F
b110 G
b110 p
1"
#600000000000000
0"
#650000000000000
1$
b1000000001 *
b1000000001 z
b1000000001 ~
0'
b1000000001 A
b1000000001 S
b1000000001 f
b1000000001 |
b1000000001 `
b10000000000 ^
b100000000 [
b1 U
b110 ,
b110 R
b1 >
b1 K
b1 Q
b110 B
b110 d
1=
13
00
0:
b11000000110 e
b1111111111111111111111111111111111111111111111111111110111111110 a
b1000000001 W
b1000000001 O
b1000000001 N
b1 <
b0 ;
b1000000001 T
b1000000000 ]
b1000000000 \
b1000000000 V
b1 8
b1 J
b1 s
b1000000000 @
b1000000000 H
b1000000000 P
b1000 2
b1000 t
b1 7
b0 6
b1000000000 /
b1000000000 I
b1000000000 x
b10 E
b10 u
b1000000000 c
b1000 1
b1000 r
b100000000100000000000001000000000 5
b100000000100000000000001000000000 q
b111 F
b111 G
b111 p
1"
#700000000000000
0"
#750000000000000
03
1-
b101000000110 e
b1001100 4
b1001100 i
b1001100 }
b1001100 (
b1001100 k
b1001 2
b1001 t
b10 C
b10 w
b100000000 c
b1001 1
b1001 r
b100000000100000000010000100000000 5
b100000000100000000010000100000000 q
b1000 F
b1000 G
b1000 p
1"
#800000000000000
0"
#850000000000000
0$
1'
b0 *
b0 z
b0 ~
b1100 ,
b1100 R
0!
b0 4
b0 i
b0 }
b0 A
b0 S
b0 f
b0 |
b1100 B
b1100 d
0=
0-
10
1:
b0 `
b101000000001100 e
b1111111111111111111111111111111111111111111111111111111110110000 a
b1001100 U
b1001111 W
b1001111 O
b1001111 N
b0 M
b10110000000001 <
b1001100 >
b1001100 K
b1001100 Q
b1011 ;
b1001111 T
b11100100 ]
b11100100 \
b0 ^
b0 [
b11 V
b1011 8
b1011 J
b1011 s
b11 @
b11 H
b11 P
b1010 2
b1010 t
b10110000000001 7
b1011 6
b0 C
b0 w
b11 /
b11 I
b11 x
b1100000 E
b1100000 u
b10000100001 c
b1010 1
b1010 r
b1011000000000100011000000000000000010000100001 5
b1011000000000100011000000000000000010000100001 q
b1001 F
b1001 G
b1001 p
1"
#900000000000000
0"
#950000000000000
1!
1$
b1 *
b1 z
b1 ~
0'
b1001100 4
b1001100 i
b1001100 }
b1 A
b1 S
b1 f
b1 |
b1 `
b1 Z
b1 b
b1111111111111111111111111111111111111111111111111111111111111111 a
b0 W
b0 O
b0 N
b110000000000 <
b11 ;
b0 U
b0 T
b0 ]
b0 \
b0 V
b11 8
b11 J
b11 s
b0 >
b0 K
b0 Q
b0 @
b0 H
b0 P
b11 2
b11 t
b110000000000 7
b11 6
b0 .
b0 L
b0 n
b0 y
b0 D
b0 v
b0 /
b0 I
b0 x
b0 E
b0 u
b1011 1
b1011 r
b11000000000000000000000000000000010000100001 5
b11000000000000000000000000000000010000100001 q
b1010 F
b1010 G
b1010 p
1"
#1000000000000000
0"
#1050000000000000
b1 `
b0 Z
b0 b
b1111111111111111111111111111111111111111111111111111111111111110 a
b1 W
b1 O
b1 N
b1 T
b1 U
b110 ,
b110 R
b1 >
b1 K
b1 Q
0!
b1001100 *
b1001100 z
b1001100 ~
b110 B
b110 d
1=
1-
00
1+
b110101000000110 e
b10000000000 <
b1 ;
b100 2
b100 t
b1 8
b1 J
b1 s
b10000000000 7
b1 6
b1 C
b1 w
b1100000000 c
b100 1
b100 r
b1000000000000000000000000000001001100000000 5
b1000000000000000000000000000001001100000000 q
b11 F
b11 G
b11 p
1"
#1100000000000000
0"
#1150000000000000
b1 Z
b1 b
b1001100 M
b1100 ,
b1100 R
1!
b1 *
b1 z
b1 ~
b1001100 4
b1001100 i
b1001100 }
b1 A
b1 S
b1 f
b1 |
b1100 B
b1100 d
0=
0-
10
0+
b1 `
b101000000001100 e
b1111111111111111111111111111111111111111111111111111111111111111 a
b1001100 U
b10011000 W
b0 O
b1001100 N
b110001100001 <
b11 ;
b1001100 >
b1001100 K
b1001100 Q
b10011000 T
b1011010010000 ]
b1011010010000 \
b0 ^
b0 [
b1001100 V
b11 8
b11 J
b11 s
b1001100 @
b1001100 H
b1001100 P
b11 2
b11 t
b110001100001 7
b11 6
b0 C
b0 w
b1001100 .
b1001100 L
b1001100 n
b1001100 y
b1100001 D
b1100001 v
b1001100 /
b1001100 I
b1001100 x
b1 E
b1 u
b10000100001 c
b101 1
b101 r
b11000110000100000000010000000000010000100001 5
b11000110000100000000010000000000010000100001 q
b100 F
b100 G
b100 p
1"
#1200000000000000
0"
#1250000000000000
b1 `
b0 Z
b0 b
b1111111111111111111111111111111111111111111111111111111111111110 a
b1 O
b110 ,
b110 R
0!
b1001100 *
b1001100 z
b1001100 ~
b110 B
b110 d
1=
1-
00
1+
b110101000000110 e
b1 W
b1 N
b0 M
b10000000000 <
b1 ;
b100 2
b100 t
b1 U
b1 T
b0 ]
b0 \
b0 V
b1 8
b1 J
b1 s
b1 >
b1 K
b1 Q
b0 @
b0 H
b0 P
b10000000000 7
b1 6
b1 C
b1 w
b0 .
b0 L
b0 n
b0 y
b0 D
b0 v
b0 /
b0 I
b0 x
b0 E
b0 u
b1100000000 c
b100 1
b100 r
b1000000000000000000000000000001001100000000 5
b1000000000000000000000000000001001100000000 q
b11 F
b11 G
b11 p
1"
#1300000000000000
0"
#1350000000000000
b1 Z
b1 b
b1001100 M
b1100 ,
b1100 R
1!
b1 *
b1 z
b1 ~
b1001100 4
b1001100 i
b1001100 }
b1 A
b1 S
b1 f
b1 |
b1100 B
b1100 d
0=
0-
10
0+
b1 `
b101000000001100 e
b1111111111111111111111111111111111111111111111111111111111111111 a
b1001100 U
b10011000 W
b0 O
b1001100 N
b110001100001 <
b11 ;
b1001100 >
b1001100 K
b1001100 Q
b10011000 T
b1011010010000 ]
b1011010010000 \
b0 ^
b0 [
b1001100 V
b11 8
b11 J
b11 s
b1001100 @
b1001100 H
b1001100 P
b11 2
b11 t
b110001100001 7
b11 6
b0 C
b0 w
b1001100 .
b1001100 L
b1001100 n
b1001100 y
b1100001 D
b1100001 v
b1001100 /
b1001100 I
b1001100 x
b1 E
b1 u
b10000100001 c
b101 1
b101 r
b11000110000100000000010000000000010000100001 5
b11000110000100000000010000000000010000100001 q
b100 F
b100 G
b100 p
1"
#1400000000000000
0"
#1450000000000000
b1 `
b0 Z
b0 b
b1111111111111111111111111111111111111111111111111111111111111110 a
b1 O
b110 ,
b110 R
0!
b1001100 *
b1001100 z
b1001100 ~
b110 B
b110 d
1=
1-
00
1+
b110101000000110 e
b1 W
b1 N
b0 M
b10000000000 <
b1 ;
b100 2
b100 t
b1 U
b1 T
b0 ]
b0 \
b0 V
b1 8
b1 J
b1 s
b1 >
b1 K
b1 Q
b0 @
b0 H
b0 P
b10000000000 7
b1 6
b1 C
b1 w
b0 .
b0 L
b0 n
b0 y
b0 D
b0 v
b0 /
b0 I
b0 x
b0 E
b0 u
b1100000000 c
b100 1
b100 r
b1000000000000000000000000000001001100000000 5
b1000000000000000000000000000001001100000000 q
b11 F
b11 G
b11 p
1"
#1500000000000000
0"
